accuhitdb/__init__.py
accuhitdb/dbs/__init__.py
accuhitdb/dbs/mongodb/__init__.py
accuhitdb/dbs/mongodb/mongo_base.py
accuhitdb/dbs/mysql/__init__.py
accuhitdb/dbs/mysql/mysql_base.py
accuhitdb/dbs/opensearch/__init__.py
accuhitdb/dbs/pgdb/__init__.py
accuhitdb/dbs/pgdb/pgdb_base.py
accuhitdb/dbs/redis/__init__.py
accuhit_db-0.9.1.dist-info/METADATA
accuhit_db-0.9.1.dist-info/WHEEL
accuhit_db-0.9.1.dist-info/top_level.txt
accuhit_db-0.9.1.dist-info/RECORD
